kapil_bhai.py
kapil_bhai-0.2.0.dist-info/METADATA
kapil_bhai-0.2.0.dist-info/WHEEL
kapil_bhai-0.2.0.dist-info/top_level.txt
kapil_bhai-0.2.0.dist-info/RECORD
