Metadata-Version: 2.4
Name: kapil_bhai
Version: 0.2.0
Summary: its about kapill bhai
Author-email: Prasoon <prasoonrajput4218@gmail.com>
License: MIT
Project-URL: Homepage, https://github.com/yourusername/mypackage
Requires-Python: >=3.7
Requires-Dist: requests
